CHANGELOG.txt
LICENSE.txt
MANIFEST.in
README.md
requirements.txt
setup.cfg
setup.py
variantbreak/__init__.py
variantbreak/input.py
variantbreak/parse.py
variantbreak/valid.py
variantbreak/variant_break.py
variantbreak/variantbreak
variantbreak/version.py
variantbreak.egg-info/PKG-INFO
variantbreak.egg-info/SOURCES.txt
variantbreak.egg-info/dependency_links.txt
variantbreak.egg-info/requires.txt
variantbreak.egg-info/top_level.txt