Metadata-Version: 2.1
Name: variantbreak
Version: 1.0.4
Summary: Structural variant analyzer for data visualization on VariantMap
Home-page: https://github.com/cytham/variantbreak
Author: Tham Cheng Yong
Author-email: chengyong.tham@u.nus.edu
License: gpl-3.0
Download-URL: https://github.com/cytham/variantbreak/releases
Keywords: variantbreak,structural variant,sv,breakend,annotation,nanovar,nanopore,long read,variantmap,filter
Platform: UNKNOWN
Classifier: Operating System :: POSIX :: Linux
Classifier: Programming Language :: Python :: 3.6
Classifier: Programming Language :: Python :: 3.7
Classifier: License :: OSI Approved :: GNU General Public License v3 (GPLv3)
Classifier: Topic :: Scientific/Engineering :: Bio-Informatics
Requires-Python: >=3.6
